django_warmama-1.0.0.dist-info/WHEEL
django_warmama-1.0.0.dist-info/metadata.json
django_warmama-1.0.0.dist-info/METADATA
django_warmama-1.0.0.dist-info/RECORD
django_warmama-1.0.0.dist-info/top_level.txt
django_warmama-1.0.0.dist-info/DESCRIPTION.rst
warmama/decorators.py
warmama/fields.py
warmama/conf.py
warmama/exceptions.py
warmama/serializers.py
warmama/admin.py
warmama/views.py
warmama/models.py
warmama/__init__.py
warmama/urls.py
warmama/fixtures/weapons.json
warmama/fixtures/gametypes.json
warmama/migrations/0001_initial.py
warmama/migrations/__init__.py
warmama/migrations/__pycache__/0001_initial.cpython-34.pyc
warmama/migrations/__pycache__/__init__.cpython-34.pyc
warmama/__pycache__/urls.cpython-34.pyc
warmama/__pycache__/conf.cpython-34.pyc
warmama/__pycache__/fields.cpython-34.pyc
warmama/__pycache__/admin.cpython-34.pyc
warmama/__pycache__/exceptions.cpython-34.pyc
warmama/__pycache__/serializers.cpython-34.pyc
warmama/__pycache__/models.cpython-34.pyc
warmama/__pycache__/decorators.cpython-34.pyc
warmama/__pycache__/__init__.cpython-34.pyc
warmama/__pycache__/views.cpython-34.pyc
warmama/__pycache__/settings.cpython-34.pyc
